wukongbaobao/__init__.py
wukongbaobao/__main__.py
wukongbaobao/conf/__init__.py
wukongbaobao/conf/arg.py
wukongbaobao/conf/output.py
wukongbaobao/mathematics/__init__.py
wukongbaobao/mathematics/question.py
wukongbaobao/mathematics/template.py
wukongbaobao/tests/test1.py
wukongbaobao/view/printer.py
wukongbaobao-1.0.10.dist-info/entry_points.txt
wukongbaobao-1.0.10.dist-info/LICENSE
wukongbaobao-1.0.10.dist-info/WHEEL
wukongbaobao-1.0.10.dist-info/METADATA
wukongbaobao-1.0.10.dist-info/RECORD
