Metadata-Version: 2.1
Name: wukongbaobao
Version: 1.0.10
Summary: Wukongbaobao is a program that helps parents flexibly generate test questions for their children. The tool is written in Python.
Keywords: education,math,learn,kids-learn,kids-education
Author: qiqilelebaobao
Author-email: qiqilelebaobao <qiqilelebaobao@163.com>
Requires-Python: >=3.6
Classifier: Programming Language :: Python :: 3
Classifier: License :: OSI Approved :: Apache Software License
Classifier: Operating System :: OS Independent
Classifier: Topic :: Education
Classifier: Topic :: Software Development
Classifier: Natural Language :: Chinese (Simplified)
Classifier: Natural Language :: English
Requires-Dist: python-docx
Project-URL: Homepage, https://github.com/qiqilelebaobao/wukongbaobao
Project-URL: Issues, https://github.com/qiqilelebaobao/wukongbaobao/issues
Project-URL: Repository, https://github.com/qiqilelebaobao/wukongbaobao
